unitlib/__init__.py
unitlib/backwards_compatibility.py
unitlib/matplotlib_support.py
unitlib/prefixes.py
unitlib/type_aliases.py
unitlib/util.py
unitlib/core_objects/__init__.py
unitlib/core_objects/array.py
unitlib/core_objects/quantity.py
unitlib/core_objects/type_aliases.py
unitlib/core_objects/unit.py
unitlib/core_objects/util.py
unitlib/core_objects/unit_internals/__init__.py
unitlib/core_objects/unit_internals/compound_unit.py
unitlib/core_objects/unit_internals/powered_unit_atom.py
unitlib/core_objects/unit_internals/unit_atom.py
unitlib/ufunc_handling/__init__.py
unitlib/ufunc_handling/add_subtract.py
unitlib/ufunc_handling/compare.py
unitlib/ufunc_handling/divide.py
unitlib/ufunc_handling/multiply.py
unitlib/ufunc_handling/power.py
unitlib/ufunc_handling/support/__init__.py
unitlib/ufunc_handling/support/make_output.py
unitlib/ufunc_handling/support/registry.py
unitlib/ufunc_handling/support/ufunc_args.py
yunit/__init__.py
yunit/backwards_compatibility.py
yunit/matplotlib_support.py
yunit/prefixes.py
yunit/test.py
yunit/type_aliases.py
yunit/util.py
yunit/array/__init__.py
yunit/array/array.py
yunit/array/quantity.py
yunit/core_objects/_1_array.py
yunit/core_objects/_2_quantity.py
yunit/core_objects/_3_unit.py
yunit/core_objects/__init__.py
yunit/core_objects/ufunc.py
yunit/core_objects/unit_internals/_1_unit_atom.py
yunit/core_objects/unit_internals/_2_powered_unit_atom.py
yunit/core_objects/unit_internals/_3_compound_unit.py
yunit/core_objects/unit_internals/__init__.py
yunit/unit/_01_base_class.py
yunit/unit/_02_simple_unit.py
yunit/unit/_03_powered_unit.py
yunit/unit/_04_compound_unit.py
yunit/unit/__init__.py
yunit/unit/prefixes.py
unitlib-0.3.dist-info/METADATA
unitlib-0.3.dist-info/WHEEL
unitlib-0.3.dist-info/top_level.txt
unitlib-0.3.dist-info/RECORD
