Metadata-Version: 2.1
Name: unitlib
Version: 0.3
Summary: 📐 Physical units for NumPy arrays ⏱ Fast • Simple • High voltage
Home-page: https://github.com/tfiers/unitlib
Author: Tomas Fiers
Author-email: tomas.fiers@gmail.com
License: UNKNOWN
Project-URL: Source Code, https://github.com/tfiers/unitlib
Platform: UNKNOWN
Classifier: License :: OSI Approved :: MIT License
Classifier: Programming Language :: Python :: 3
Classifier: Operating System :: OS Independent
Requires-Python: >= 3.6
Requires-Dist: numpy (>=1.17)
Requires-Dist: dataclasses ; python_version < "3.7"
Requires-Dist: typing-extensions ; python_version < "3.8"
